nonconvexAG_GPU/__init__.py
nonconvexAG_GPU-1.0.8.dist-info/LICENSE
nonconvexAG_GPU-1.0.8.dist-info/METADATA
nonconvexAG_GPU-1.0.8.dist-info/WHEEL
nonconvexAG_GPU-1.0.8.dist-info/top_level.txt
nonconvexAG_GPU-1.0.8.dist-info/RECORD
