Metadata-Version: 2.1
Name: nonconvexAG-GPU
Version: 1.0.8
Summary: (GPU version) Implementation of accelerated gradient algorithm with strong rules for (high-dimensional) nonconvex sparse learning problems.
Author-email: Kai Yang <kai.yang2@mail.mcgill.ca>
License: GNU AFFERO GENERAL PUBLIC LICENSE
Project-URL: Homepage, https://github.com/Kaiyangshi-Ito/nonconvexAG
Project-URL: Bug Tracker, https://github.com/Kaiyangshi-Ito/nonconvexAG/issues
Classifier: Programming Language :: Python :: 3
Classifier: License :: OSI Approved :: GNU Affero General Public License v3 or later (AGPLv3+)
Classifier: Operating System :: OS Independent
Requires-Python: >=3.7
License-File: LICENSE
Requires-Dist: cupy (>=8.3.0)
